tnsu/__init__.py
tnsu/examples.py
tnsu/math_objects.py
tnsu/simple_update.py
tnsu/structure_matrix_constructor.py
tnsu/tensor_network.py
tnsu/utils.py
tnsu/networks/AFH_10x10_obc_D_4.pkl
tnsu/networks/AFH_20x20_obc_D_4.pkl
tnsu/networks/AFH_20x20_pbc_D_4.pkl
tnsu-1.0.5.dist-info/licenses/LICENSE.txt
tnsu-1.0.5.dist-info/METADATA
tnsu-1.0.5.dist-info/WHEEL
tnsu-1.0.5.dist-info/top_level.txt
tnsu-1.0.5.dist-info/zip-safe
tnsu-1.0.5.dist-info/RECORD
