Metadata-Version: 2.4
Name: tnsu
Version: 1.0.5
Summary: A package for Tensor-Networks Simple-Update simulations of quantum wave functions representations
Home-page: https://github.com/RoyElkabetz/Tensor-Networks-Simple-Update
Author: Roy Elkabetz
Author-email: elkabetzroy@gmail.com
Keywords: Tensor-Networks,Simple-Update,Quantum-Information
Classifier: License :: OSI Approved :: MIT License
Classifier: Programming Language :: Python
Classifier: Programming Language :: Python :: 3
Classifier: Programming Language :: Python :: 3.10
Classifier: Programming Language :: Python :: 3.11
Classifier: Programming Language :: Python :: 3.12
Requires-Python: >=3.10
License-File: LICENSE.txt
Requires-Dist: matplotlib
Requires-Dist: numpy
Requires-Dist: scipy
Requires-Dist: ncon
Provides-Extra: dev
Requires-Dist: pytest; extra == "dev"
Dynamic: license-file
